LICENSE.txt
README.md
setup.cfg
setup.py
Topsis_Puneet_102003135/__init__.py
Topsis_Puneet_102003135/topsis_102003135.py
Topsis_Puneet_102003135.egg-info/PKG-INFO
Topsis_Puneet_102003135.egg-info/SOURCES.txt
Topsis_Puneet_102003135.egg-info/dependency_links.txt
Topsis_Puneet_102003135.egg-info/requires.txt
Topsis_Puneet_102003135.egg-info/top_level.txt